bumpit/__init__.py
bumpit/console/__init__.py
bumpit/console/cli.py
bumpit/core/__init__.py
bumpit/core/bumpit.py
bumpit/core/folder.py
bumpit/core/vcs.py
bumpit/core/config/__init__.py
bumpit/core/config/commit.py
bumpit/core/config/strategy.py
bumpit/core/config/tag.py
bumpit/core/versions/__init__.py
bumpit/core/versions/strategy.py
bumpit/core/versions/calver/__init__.py
bumpit/core/versions/calver/calver.py
bumpit/core/versions/calver/constants.py
bumpit/core/versions/calver/formatters.py
bumpit/core/versions/calver/matchers.py
bumpit/core/versions/calver/parsers.py
bumpit/core/versions/calver/transformers.py
bumpit/core/versions/semver/__init__.py
bumpit/core/versions/semver/parsers.py
bumpit/core/versions/semver/semver.py
bumpit/core/versions/semver/transformers.py
tests/__init__.py
tests/unit/__init__.py
tests/unit/core/__init__.py
tests/unit/core/test_bumpit.py
tests/unit/core/test_config.py
tests/unit/core/test_folder.py
tests/unit/core/test_vcs.py
tests/unit/core/test_versions.py
tests/unit/core/config/__init__.py
tests/unit/core/config/test_commit.py
tests/unit/core/config/test_strategy.py
tests/unit/core/config/test_tag.py
tests/unit/core/versions/__init__.py
tests/unit/core/versions/test_next_version_calver.py
tests/unit/core/versions/test_next_version_semver.py
tests/unit/core/versions/calver/__init__.py
tests/unit/core/versions/calver/test_matchers.py
tests/unit/core/versions/calver/test_parsers.py
tests/unit/core/versions/calver/test_transformers.py
tests/unit/core/versions/semver/__init__.py
tests/unit/core/versions/semver/test_parsers.py
tests/unit/core/versions/semver/test_transformers.py
bumpit-0.8.0.dist-info/LICENSE
bumpit-0.8.0.dist-info/METADATA
bumpit-0.8.0.dist-info/WHEEL
bumpit-0.8.0.dist-info/entry_points.txt
bumpit-0.8.0.dist-info/top_level.txt
bumpit-0.8.0.dist-info/RECORD
