Metadata-Version: 2.1
Name: bumpit
Version: 0.8.0
Summary: A small command line tool to bump tracked versions in your repository.
Home-page: https://github.com/mobiusbyte/bumpit
Author: Jill San Luis
Author-email: jill@mobiusbyte.com
License: MIT
Project-URL: Code, https://github.com/mobiusbyte/bumpit
Project-URL: Issue tracker, https://github.com/mobiusbyte/bumpit/issues
Platform: UNKNOWN
Classifier: Programming Language :: Python :: 3
Classifier: Programming Language :: Python :: 3.7
Requires-Python: >=3.7
Requires-Dist: click
Requires-Dist: pyyaml
